rtd/404.html
rtd/__init__.py
rtd/base.html
rtd/breadcrumbs.html
rtd/css/fonts/Roboto-Slab-Bold.woff
rtd/css/fonts/Roboto-Slab-Bold.woff2
rtd/css/fonts/Roboto-Slab-Regular.woff
rtd/css/fonts/Roboto-Slab-Regular.woff2
rtd/css/fonts/fontawesome-webfont.eot
rtd/css/fonts/fontawesome-webfont.svg
rtd/css/fonts/fontawesome-webfont.ttf
rtd/css/fonts/fontawesome-webfont.woff
rtd/css/fonts/fontawesome-webfont.woff2
rtd/css/fonts/lato-bold-italic.woff
rtd/css/fonts/lato-bold-italic.woff2
rtd/css/fonts/lato-bold.woff
rtd/css/fonts/lato-bold.woff2
rtd/css/fonts/lato-normal-italic.woff
rtd/css/fonts/lato-normal-italic.woff2
rtd/css/fonts/lato-normal.woff
rtd/css/fonts/lato-normal.woff2
rtd/css/theme.css
rtd/css/theme_extra.css
rtd/footer.html
rtd/github_icon.png
rtd/img/favicon.ico
rtd/js/html5shiv.min.js
rtd/js/jquery-3.6.0.min.js
rtd/js/theme.js
rtd/js/theme_extra.js
rtd/js/version-select.js
rtd/locales/de/LC_MESSAGES/messages.po
rtd/locales/es/LC_MESSAGES/messages.po
rtd/locales/fa/LC_MESSAGES/messages.po
rtd/locales/fr/LC_MESSAGES/messages.po
rtd/locales/id/LC_MESSAGES/messages.po
rtd/locales/it/LC_MESSAGES/messages.po
rtd/locales/ja/LC_MESSAGES/messages.po
rtd/locales/pt_BR/LC_MESSAGES/messages.po
rtd/locales/ru/LC_MESSAGES/messages.po
rtd/locales/tr/LC_MESSAGES/messages.po
rtd/locales/uk/LC_MESSAGES/messages.po
rtd/locales/zh_CN/LC_MESSAGES/messages.po
rtd/locales/zh_TW/LC_MESSAGES/messages.po
rtd/main.html
rtd/mkdocs_theme.yml
rtd/nav.html
rtd/search.html
rtd/searchbox.html
rtd/toc.html
rtd/versions.html
mkdocs_rtd-0.0.15.dist-info/METADATA
mkdocs_rtd-0.0.15.dist-info/WHEEL
mkdocs_rtd-0.0.15.dist-info/entry_points.txt
mkdocs_rtd-0.0.15.dist-info/RECORD
